{"_type":"export","__export_format":4,"__export_date":"2020-06-13T01:48:41.973Z","__export_source":"insomnia.desktop.app:v2020.2.1","resources":[{"_id":"req_be4145f0e2404074a103165ccbc09ef0","authentication":{},"body":{},"created":1592012866777,"description":"","headers":[],"isPrivate":false,"metaSortKey":-1592012866777,"method":"GET","modified":1592012874841,"name":"Ping","parameters":[],"parentId":"wrk_4d3dd64b3f404b8ab1fda0dbd5d1d177","settingDisableRenderRequestBody":false,"settingEncodeUrl":true,"settingFollowRedirects":"global","settingRebuildPath":true,"settingSendCookies":true,"settingStoreCookies":true,"url":"https://encryptii-server.herokuapp.com/ping","_type":"request"},{"_id":"wrk_4d3dd64b3f404b8ab1fda0dbd5d1d177","created":1590826897341,"description":"","modified":1590826897341,"name":"Insomnia","parentId":null,"scope":null,"_type":"workspace"},{"_id":"req_5319b895ba7f4ef299e0d81a3f3fd249","authentication":{},"body":{},"created":1591349022185,"description":"","headers":[],"isPrivate":false,"metaSortKey":-1592012024941,"method":"GET","modified":1592012877146,"name":"Encrypt","parameters":[{"description":"","id":"pair_f16152ebb22d4a4e83df95d78228257b","multiline":true,"name":"msg","type":"text","value":"# Dillinger\n\n[![N|Solid](https://cldup.com/dTxpPi9lDf.thumb.png)](https://nodesource.com/products/nsolid)\n\n[![Build Status](https://travis-ci.org/joemccann/dillinger.svg?branch=master)](https://travis-ci.org/joemccann/dillinger)\n\nDillinger is a cloud-enabled, mobile-ready, offline-storage, AngularJS powered HTML5 Markdown editor.\n\n  - Type some Markdown on the left\n  - See HTML in the right\n  - Magic\n\n# New Features!\n\n  - Import a HTML file and watch it magically convert to Markdown\n  - Drag and drop images (requires your Dropbox account be linked)\n\n\nYou can also:\n  - Import and save files from GitHub, Dropbox, Google Drive and One Drive\n  - Drag and drop markdown and HTML files into Dillinger\n  - Export documents as Markdown, HTML and PDF\n\nMarkdown is a lightweight markup language based on the formatting conventions that people naturally use in email.  As [John Gruber] writes on the [Markdown site][df1]\n\n> The overriding design goal for Markdown's\n> formatting syntax is to make it as readable\n> as possible. The idea is that a\n> Markdown-formatted document should be\n> publishable as-is, as plain text, without\n> looking like it's been marked up with tags\n> or formatting instructions.\n\nThis text you see here is *actually* written in Markdown! To get a feel for Markdown's syntax, type some text into the left window and watch the results in the right.\n\n### Tech\n\nDillinger uses a number of open source projects to work properly:\n\n* [AngularJS] - HTML enhanced for web apps!\n* [Ace Editor] - awesome web-based text editor\n* [markdown-it] - Markdown parser done right. Fast and easy to extend.\n* [Twitter Bootstrap] - great UI boilerplate for modern web apps\n* [node.js] - evented I/O for the backend\n* [Express] - fast node.js network app framework [@tjholowaychuk]\n* [Gulp] - the streaming build system\n* [Breakdance](https://breakdance.github.io/breakdance/) - HTML to Markdown converter\n* [jQuery] - duh\n\nAnd of course Dillinger itself is open source with a [public repository][dill]\n on GitHub.\n\n### Installation\n\nDillinger requires [Node.js](https://nodejs.org/) v4+ to run.\n\nInstall the dependencies and devDependencies and start the server.\n\n```sh\n$ cd dillinger\n$ npm install -d\n$ node app\n```\n\nFor production environments...\n\n```sh\n$ npm install --production\n$ NODE_ENV=production node app\n```\n\n### Plugins\n\nDillinger is currently extended with the following plugins. Instructions on how to use them in your own application are linked below.\n\n| Plugin | README |\n| ------ | ------ |\n| Dropbox | [plugins/dropbox/README.md][PlDb] |\n| GitHub | [plugins/github/README.md][PlGh] |\n| Google Drive | [plugins/googledrive/README.md][PlGd] |\n| OneDrive | [plugins/onedrive/README.md][PlOd] |\n| Medium | [plugins/medium/README.md][PlMe] |\n| Google Analytics | [plugins/googleanalytics/README.md][PlGa] |\n\n\n### Development\n\nWant to contribute? Great!\n\nDillinger uses Gulp + Webpack for fast developing.\nMake a change in your file and instantaneously see your updates!\n\nOpen your favorite Terminal and run these commands.\n\nFirst Tab:\n```sh\n$ node app\n```\n\nSecond Tab:\n```sh\n$ gulp watch\n```\n\n(optional) Third:\n```sh\n$ karma test\n```\n#### Building for source\nFor production release:\n```sh\n$ gulp build --prod\n```\nGenerating pre-built zip archives for distribution:\n```sh\n$ gulp build dist --prod\n```\n### Docker\nDillinger is very easy to install and deploy in a Docker container.\n\nBy default, the Docker will expose port 8080, so change this within the Dockerfile if necessary. When ready, simply use the Dockerfile to build the image.\n\n```sh\ncd dillinger\ndocker build -t joemccann/dillinger:${package.json.version} .\n```\nThis will create the dillinger image and pull in the necessary dependencies. Be sure to swap out `${package.json.version}` with the actual version of Dillinger.\n\nOnce done, run the Docker image and map the port to whatever you wish on your host. In this example, we simply map port 8000 of the host to port 8080 of the Docker (or whatever port was exposed in the Dockerfile):\n\n```sh\ndocker run -d -p 8000:8080 --restart=\"always\" <youruser>/dillinger:${package.json.version}\n```\n\nVerify the deployment by navigating to your server address in your preferred browser.\n\n```sh\n127.0.0.1:8000\n```\n\n#### Kubernetes + Google Cloud\n\nSee [KUBERNETES.md](https://github.com/joemccann/dillinger/blob/master/KUBERNETES.md)\n\n\n### Todos\n\n - Write MORE Tests\n - Add Night Mode\n\nLicense\n----\n\nMIT\n\n\n**Free Software, Hell Yeah!**\n\n[//]: # (These are reference links used in the body of this note and get stripped out when the markdown processor does its job. There is no need to format nicely because it shouldn't be seen. Thanks SO - http://stackoverflow.com/questions/4823468/store-comments-in-markdown-syntax)\n\n\n   [dill]: <https://github.com/joemccann/dillinger>\n   [git-repo-url]: <https://github.com/joemccann/dillinger.git>\n   [john gruber]: <http://daringfireball.net>\n   [df1]: <http://daringfireball.net/projects/markdown/>\n   [markdown-it]: <https://github.com/markdown-it/markdown-it>\n   [Ace Editor]: <http://ace.ajax.org>\n   [node.js]: <http://nodejs.org>\n   [Twitter Bootstrap]: <http://twitter.github.com/bootstrap/>\n   [jQuery]: <http://jquery.com>\n   [@tjholowaychuk]: <http://twitter.com/tjholowaychuk>\n   [express]: <http://expressjs.com>\n   [AngularJS]: <http://angularjs.org>\n   [Gulp]: <http://gulpjs.com>\n\n   [PlDb]: <https://github.com/joemccann/dillinger/tree/master/plugins/dropbox/README.md>\n   [PlGh]: <https://github.com/joemccann/dillinger/tree/master/plugins/github/README.md>\n   [PlGd]: <https://github.com/joemccann/dillinger/tree/master/plugins/googledrive/README.md>\n   [PlOd]: <https://github.com/joemccann/dillinger/tree/master/plugins/onedrive/README.md>\n   [PlMe]: <https://github.com/joemccann/dillinger/tree/master/plugins/medium/README.md>\n   [PlGa]: <https://github.com/RahulHP/dillinger/blob/master/plugins/googleanalytics/README.md>\n"}],"parentId":"wrk_4d3dd64b3f404b8ab1fda0dbd5d1d177","settingDisableRenderRequestBody":false,"settingEncodeUrl":true,"settingFollowRedirects":"global","settingRebuildPath":true,"settingSendCookies":true,"settingStoreCookies":true,"url":"https://encryptii-server.herokuapp.com/encrypt","_type":"request"},{"_id":"req_62d6ebf792234a51a5aeb747b1d93dbe","authentication":{},"body":{},"created":1592011183105,"description":"","headers":[],"isPrivate":false,"metaSortKey":-1592011183105,"method":"GET","modified":1592011680558,"name":"Decrypt","parameters":[{"description":"","id":"pair_035d93cd6e5e49a7913a2ce3fb2c0ca5","name":"dec","value":"gAAAAABe5CuGtpG9qBJbx7qmrU2bbieA4egywBkFQyzEIlyfh7QQgsuCGBMZsqvCqli17x5fOR7Xw5kvxPgF9XmsraL6OnmNdQ=="},{"description":"","id":"pair_ed3960e99dd54417a5e9df8b0f98103e","name":"destroy","value":"true"}],"parentId":"wrk_4d3dd64b3f404b8ab1fda0dbd5d1d177","settingDisableRenderRequestBody":false,"settingEncodeUrl":true,"settingFollowRedirects":"global","settingRebuildPath":true,"settingSendCookies":true,"settingStoreCookies":true,"url":"https://encryptii-server.herokuapp.com/decrypt","_type":"request"},{"_id":"env_74fdce05a8d359a540ac6a0e47c8dfbe98b94bb5","color":null,"created":1590826897387,"data":{},"dataPropertyOrder":null,"isPrivate":false,"metaSortKey":1590826897387,"modified":1590826897387,"name":"Base Environment","parentId":"wrk_4d3dd64b3f404b8ab1fda0dbd5d1d177","_type":"environment"},{"_id":"jar_74fdce05a8d359a540ac6a0e47c8dfbe98b94bb5","cookies":[],"created":1590826897391,"modified":1590826897391,"name":"Default Jar","parentId":"wrk_4d3dd64b3f404b8ab1fda0dbd5d1d177","_type":"cookie_jar"},{"_id":"spc_2c375fdb2a024a43b9ceefbacb777e70","contentType":"yaml","contents":"","created":1592011169736,"fileName":"Insomnia","modified":1592011169736,"parentId":"wrk_4d3dd64b3f404b8ab1fda0dbd5d1d177","_type":"api_spec"},{"_id":"env_9af024bed9934c09a2e8deb132b02e7c","color":"#73fa79","created":1591348978641,"data":{},"dataPropertyOrder":null,"isPrivate":false,"metaSortKey":1591348978641,"modified":1591349005633,"name":"Encryptii","parentId":"env_74fdce05a8d359a540ac6a0e47c8dfbe98b94bb5","_type":"environment"}]}